mneia_isbn/__init__.py
mneia_isbn/exceptions.py
mneia_isbn/groups.py
mneia_isbn/isbn.py
mneia_isbn/constants/__init__.py
mneia_isbn/constants/_publishers.py
mneia_isbn/constants/publishers.py
mneia_isbn/constants/ranges.py
mneia_isbn/utils/__init__.py
mneia_isbn/utils/conversion.py
mneia_isbn/utils/validation.py
mneia_isbn-0.0.3.dist-info/licenses/LICENSE
mneia_isbn-0.0.3.dist-info/METADATA
mneia_isbn-0.0.3.dist-info/WHEEL
mneia_isbn-0.0.3.dist-info/top_level.txt
mneia_isbn-0.0.3.dist-info/RECORD
