Metadata-Version: 2.4
Name: mneia-isbn
Version: 0.0.3
Summary: A collection of tools for working with ISBNs in Python.
Author-email: Marios Zindilis <marios@mneia.gr>
License-Expression: MIT
Project-URL: homepage, https://github.com/mneia-gr/mneia-isbn
Project-URL: repository, https://github.com/mneia-gr/mneia-isbn
Project-URL: issues, https://github.com/mneia-gr/mneia-isbn/issues
Project-URL: changelog, https://github.com/mneia-gr/mneia-isbn/CHANGELOG.md
Keywords: isbn,isbn10,isbn13,books
Classifier: Development Status :: 4 - Beta
Classifier: Programming Language :: Python :: 3
Classifier: Programming Language :: Python :: 3.9
Classifier: Programming Language :: Python :: 3.10
Classifier: Programming Language :: Python :: 3.11
Classifier: Programming Language :: Python :: 3.12
Classifier: Programming Language :: Python :: 3.13
Classifier: Operating System :: OS Independent
Classifier: Intended Audience :: Developers
Requires-Python: >=3.9
License-File: LICENSE
Dynamic: license-file
